trading_common/__init__.py
trading_common/_version.py
trading_common/consumer_app.py
trading_common/db.py
trading_common/kafka.py
trading_common/kafka_common.py
trading_common/outbox.py
trading_common/schema.py
trading_common/settings_kafka.py
trading_common-0.2.5.dist-info/licenses/LICENSE
trading_common-0.2.5.dist-info/METADATA
trading_common-0.2.5.dist-info/WHEEL
trading_common-0.2.5.dist-info/top_level.txt
trading_common-0.2.5.dist-info/RECORD
