Metadata-Version: 2.4
Name: trading-common
Version: 0.2.5
Summary: Common utils for trading platform (Kafka/Postgres/outbox/inbox)
Author: Trading Platform Team
License: MIT
Keywords: trading,kafka,postgres,async,outbox,inbox
Classifier: Development Status :: 3 - Alpha
Classifier: Intended Audience :: Developers
Classifier: License :: OSI Approved :: MIT License
Classifier: Programming Language :: Python :: 3
Classifier: Programming Language :: Python :: 3.10
Classifier: Programming Language :: Python :: 3.11
Classifier: Programming Language :: Python :: 3.12
Classifier: Topic :: Software Development :: Libraries :: Python Modules
Classifier: Topic :: Office/Business :: Financial :: Investment
Requires-Python: >=3.10
License-File: LICENSE
Requires-Dist: aiokafka>=0.10
Requires-Dist: asyncpg>=0.29
Requires-Dist: ujson>=5.9
Requires-Dist: trading-contracts>=0.1.0
Requires-Dist: jsonschema>=4.22
Provides-Extra: dev
Requires-Dist: pytest>=7.0; extra == "dev"
Requires-Dist: pytest-asyncio>=0.21; extra == "dev"
Requires-Dist: black>=23.0; extra == "dev"
Requires-Dist: isort>=5.12; extra == "dev"
Requires-Dist: mypy>=1.0; extra == "dev"
Requires-Dist: pytest-cov>=4.0; extra == "dev"
Requires-Dist: pre-commit>=3.0; extra == "dev"
Requires-Dist: flake8>=6.0; extra == "dev"
Dynamic: license-file
